STFTsignal/STFTsignal.py
STFTsignal/__init__.py
STFTsignal-0.1.0.dist-info/METADATA
STFTsignal-0.1.0.dist-info/WHEEL
STFTsignal-0.1.0.dist-info/top_level.txt
STFTsignal-0.1.0.dist-info/RECORD
