Metadata-Version: 2.1
Name: STFTsignal
Version: 0.1.0
Summary: A Python library for calculating Short-Time Fourier Transform
Home-page: https://github.com/Metaverse-Crowdsource/EEG-Chaos-Kuramoto-Neural-Net/blob/main/Higuchi_Fractal_Dimension_files/Higuchi%20Fractal%20Dimension.ipynb
Author: soul_syrup
Author-email: soul.syrupp@gmail.com
Requires-Dist: numpy
